django_tiptap/__init__.py
django_tiptap/apps.py
django_tiptap/config.py
django_tiptap/fields.py
django_tiptap/widgets.py
django_tiptap/static/django_tiptap/css/styles.css
django_tiptap/templates/forms/tiptap_textarea.html
django_tiptap-0.0.17.dist-info/LICENSE
django_tiptap-0.0.17.dist-info/WHEEL
django_tiptap-0.0.17.dist-info/METADATA
django_tiptap-0.0.17.dist-info/RECORD
