Metadata-Version: 2.1
Name: django_tiptap
Version: 0.0.17
Summary: TipTap Editor in Django 🚀
Author: Jeet Mandaliya & Max Patzelt
Author-email: django.tiptap@gmail.com
Requires-Python: >=3.5
Classifier: License :: OSI Approved :: MIT License
Requires-Dist: Django >= 2.2
Requires-Dist: black ; extra == "dev"
Requires-Dist: isort ; extra == "dev"
Requires-Dist: pre-commit ; extra == "dev"
Requires-Dist: pytest ; extra == "test"
Provides-Extra: dev
Provides-Extra: test
